<ui:UiBinder xmlns:ui='urn:ui:com.google.gwt.uibinder'
             xmlns:g='urn:import:com.google.gwt.user.client.ui'
             xmlns:paper='urn:import:com.vaadin.polymer.paper.widget'>
    <g:HTMLPanel>
        <g:HTMLPanel>
            <div class="container">
                <div class="row">
                    <div class="col-md-12">
                        <p>Polymer and bootstrap based wiki/cms project, built on GWT.</p>
                        <p>License - GPLv 3.0</p>
                        <p>Author - Gábor Percze</p>
                    </div>
                </div>
            </div>
        </g:HTMLPanel>
    </g:HTMLPanel>
</ui:UiBinder>